mylib001/__init__.py
mylib001-0.1.dist-info/LICENSE.txt
mylib001-0.1.dist-info/METADATA
mylib001-0.1.dist-info/WHEEL
mylib001-0.1.dist-info/top_level.txt
mylib001-0.1.dist-info/RECORD
